gravitorch/__init__.py
gravitorch/cli/__init__.py
gravitorch/cli/run.py
gravitorch/constants.py
gravitorch/creators/__init__.py
gravitorch/creators/core/__init__.py
gravitorch/creators/core/advanced.py
gravitorch/creators/core/base.py
gravitorch/creators/core/vanilla.py
gravitorch/creators/dataloader/__init__.py
gravitorch/creators/dataloader/base.py
gravitorch/creators/dataloader/factory.py
gravitorch/creators/dataloader/pytorch.py
gravitorch/creators/datapipe/__init__.py
gravitorch/creators/datapipe/base.py
gravitorch/creators/datapipe/chained.py
gravitorch/creators/datapipe/dictbatcher.py
gravitorch/creators/datapipe/random.py
gravitorch/creators/datapipe/sequential.py
gravitorch/creators/datapipe/vanilla.py
gravitorch/creators/dataset/__init__.py
gravitorch/creators/dataset/base.py
gravitorch/creators/dataset/vanilla.py
gravitorch/creators/datasource/__init__.py
gravitorch/creators/datasource/base.py
gravitorch/creators/datasource/vanilla.py
gravitorch/creators/lr_scheduler/__init__.py
gravitorch/creators/lr_scheduler/base.py
gravitorch/creators/lr_scheduler/factory.py
gravitorch/creators/lr_scheduler/vanilla.py
gravitorch/creators/model/__init__.py
gravitorch/creators/model/base.py
gravitorch/creators/model/compiled.py
gravitorch/creators/model/ddp.py
gravitorch/creators/model/vanilla.py
gravitorch/creators/optimizer/__init__.py
gravitorch/creators/optimizer/base.py
gravitorch/creators/optimizer/factory.py
gravitorch/creators/optimizer/noo.py
gravitorch/creators/optimizer/vanilla.py
gravitorch/creators/optimizer/zero.py
gravitorch/data/__init__.py
gravitorch/data/datacreators/__init__.py
gravitorch/data/datacreators/base.py
gravitorch/data/datacreators/caching.py
gravitorch/data/datacreators/hypercube.py
gravitorch/data/datacreators/vanilla.py
gravitorch/data/partitioners/__init__.py
gravitorch/data/partitioners/base.py
gravitorch/data/partitioners/distributed.py
gravitorch/data/partitioners/even.py
gravitorch/data/partitioners/fixed_size.py
gravitorch-0.0.23.dist-info/LICENSE
gravitorch-0.0.23.dist-info/METADATA
gravitorch-0.0.23.dist-info/WHEEL
gravitorch-0.0.23.dist-info/RECORD
