Metadata-Version: 2.1
Name: gravitorch
Version: 0.0.23
Summary: A library to train ML models with PyTorch
Home-page: https://github.com/durandtibo/gravitorch
Keywords: gravitorch
Author: Thibaut Durand
Author-email: durand.tibo+gh@gmail.com
Requires-Python: >=3.9,<3.12
Classifier: Development Status :: 2 - Pre-Alpha
Classifier: Intended Audience :: Developers
Classifier: Intended Audience :: Science/Research
Classifier: License :: OSI Approved :: BSD License
Classifier: Operating System :: POSIX :: Linux
Classifier: Programming Language :: Python :: 3
Classifier: Programming Language :: Python :: 3.9
Classifier: Programming Language :: Python :: 3.10
Classifier: Programming Language :: Python :: 3.11
Classifier: Topic :: Scientific/Engineering :: Artificial Intelligence
Provides-Extra: all
Provides-Extra: tb
Requires-Dist: colorlog (>=6.7,<6.8) ; extra == "all"
Requires-Dist: coola (>=0.0.20,<0.0.26)
Requires-Dist: hya (>=0.0.12,<0.0.15)
Requires-Dist: hydra-core (>=1.3,<1.4)
Requires-Dist: matplotlib (>=3.6,<3.9) ; extra == "all"
Requires-Dist: minevent (>=0.0.4,<0.0.6)
Requires-Dist: numpy (>=1.22,<1.27)
Requires-Dist: objectory (>=0.0.7,<0.0.9)
Requires-Dist: pillow (>=9.0,<11.0) ; extra == "all"
Requires-Dist: psutil (>=5.9,<5.10) ; extra == "all"
Requires-Dist: pytorch-ignite (>=0.4.11,<0.5)
Requires-Dist: pytorch-ignite (>=0.4.12,<0.5) ; python_version >= "3.11" and python_version < "4.0"
Requires-Dist: startorch (>=0.0.5,<0.0.8) ; extra == "all"
Requires-Dist: tabulate (>=0.9,<0.10)
Requires-Dist: tensorboard (>=2.10,<2.16) ; extra == "all" or extra == "tb"
Requires-Dist: torch (>=2.0,<2.2)
Requires-Dist: tqdm (>=4.64,<4.67) ; extra == "all"
Project-URL: Repository, https://github.com/durandtibo/gravitorch
